yijie/__init__.py
yijie/common.py
yijie/main.py
yijie/router.py
yijie-0.1.dist-info/METADATA
yijie-0.1.dist-info/RECORD
yijie-0.1.dist-info/WHEEL
yijie-0.1.dist-info/top_level.txt
